theid/__init__.py
theid/_auth.py
theid/_utils.py
theid-1.0.9.dist-info/METADATA
theid-1.0.9.dist-info/WHEEL
theid-1.0.9.dist-info/top_level.txt
theid-1.0.9.dist-info/RECORD
