Metadata-Version: 2.1
Name: theid
Version: 1.0.9
Summary: Identity Service
Home-page: https://devnull.cn
Author: Xizhen Du
Author-email: xizhendu@gmail.com
Requires-Dist: requests
